{
  "custom": {},
  "params": {},
  "props": {},
  "root": {
    "children": [
      {
        "meta": {
          "name": "EmbeddedView_0"
        },
        "position": {
          "size": "large"
        },
        "props": {
          "path": "Header"
        },
        "type": "ia.display.view"
      },
      {
        "children": [
          {
            "events": {
              "dom": {
                "onClick": {
                  "config": {
                    "id": "LeftNav",
                    "type": "toggle"
                  },
                  "scope": "C",
                  "type": "dock"
                }
              }
            },
            "meta": {
              "name": "Icon"
            },
            "position": {
              "basis": "60px"
            },
            "props": {
              "path": "material/menu"
            },
            "type": "ia.display.icon"
          }
        ],
        "meta": {
          "name": "FlexContainer"
        },
        "type": "ia.container.flex"
      }
    ],
    "meta": {
      "name": "root"
    },
    "type": "ia.container.breakpt"
  }
}